{"cameraMode":{"drawMode":0,"name":"Shaded","section":"Shading Mode"},"sceneLighting":true,"audioPlay":false,"sceneViewState":{"m_AlwaysRefresh":false,"showFog":true,"showSkybox":true,"showFlares":true,"showImageEffects":true,"showParticleSystems":true,"showVisualEffectGraphs":true,"m_FxEnabled":true},"in2DMode":false,"pivot":{"x":-0.5471168756484985,"y":1.5313619375228882,"z":-4.7592010498046879},"rotation":{"x":0.0479782298207283,"y":-0.013485333882272244,"z":0.0006448980420827866,"w":0.9987772703170776},"size":1.6877740621566773,"orthographic":false}